README.md
setup.py
mriutils/__init__.py
mriutils/test.py
mriutils/train.py
mriutils.egg-info/PKG-INFO
mriutils.egg-info/SOURCES.txt
mriutils.egg-info/dependency_links.txt
mriutils.egg-info/requires.txt
mriutils.egg-info/top_level.txt
mriutils/datasets/__init__.py
mriutils/datasets/acdc.py
mriutils/datasets/brats.py
mriutils/datasets/lvmvm.py
mriutils/datasets/mmwhs.py
mriutils/datasets/mrbrains.py
mriutils/datasets/pngs.py
mriutils/examples/__init__.py
mriutils/examples/test_ear3d_lvmvm.py
mriutils/metrics/__init__.py
mriutils/metrics/segmentation.py
mriutils/metrics/synthesis.py
mriutils/models/__init__.py
mriutils/models/cube_unet3d.py
mriutils/models/ear3d.py
mriutils/models/proximator_net.py
mriutils/models/unet.py
mriutils/models/unet3d.py
mriutils/models/modules/__init__.py
mriutils/models/modules/losses.py
mriutils/models/modules/metrics.py
mriutils/utils/__init__.py
mriutils/utils/data.py
mriutils/utils/load_data.py
mriutils/utils/norm.py
mriutils/utils/plots.py
mriutils/utils/resize.py
mriutils/utils/show.py
mriutils/utils/timer.py
mriutils/utils/tonii.py
mriutils/utils/tonpy.py