Metadata-Version: 2.1
Name: mriutils
Version: 1.2.18
Summary: A simple common utils and models package
Home-page: https://github.com/kuangmeng/MRIUtils
Author: Mengmeng Kuang
Author-email: kuangmeng@msn.com
License: UNKNOWN
Keywords: MRI-Analysis
Platform: UNKNOWN
Classifier: Programming Language :: Python :: 3
Classifier: License :: OSI Approved :: MIT License
Classifier: Operating System :: OS Independent
Classifier: Topic :: Utilities
Requires-Python: >=3.5
